{"version":1,"resource":"vscode-remote://970-cs-7914574848-default.cs-asia-southeast1-seal.cloudshell.dev/home/biswabandita_rout/Backend/app.js","entries":[{"id":"Xkd4.js","timestamp":1737526493865},{"id":"mNXy.js","timestamp":1737526520023},{"id":"oi03.js","timestamp":1737526951934},{"id":"hpiI.js","timestamp":1737527411591},{"id":"zI9N.js","source":"undoRedo.source","timestamp":1737527418447},{"id":"S7AP.js","timestamp":1737527439703},{"id":"sHQx.js","timestamp":1737533079263},{"id":"8i7A.js","timestamp":1737533175172},{"id":"4eoo.js","timestamp":1737544127142},{"id":"2uws.js","timestamp":1737547471091},{"id":"DruH.js","timestamp":1737547503276},{"id":"HIMu.js","timestamp":1737547518922},{"id":"Ersc.js","timestamp":1737548628216},{"id":"fRM4.js","source":"undoRedo.source","timestamp":1737548634811},{"id":"YJAQ.js","timestamp":1737550089177},{"id":"9pk5.js","timestamp":1737550706312},{"id":"Gll7.js","source":"undoRedo.source","timestamp":1737550711117},{"id":"2WQT.js","timestamp":1737550725191},{"id":"tenJ.js","timestamp":1737551164336},{"id":"YvXb.js","timestamp":1737552280782},{"id":"XG22.js","timestamp":1737552299892},{"id":"En0L.js","timestamp":1737553074566},{"id":"2ZMO.js","timestamp":1737553220547},{"id":"3x2G.js","timestamp":1737553505996},{"id":"bjgJ.js","timestamp":1737554711808},{"id":"ZqUW.js","source":"undoRedo.source","timestamp":1737554850382},{"id":"XrIg.js","timestamp":1737613393948},{"id":"s31G.js","timestamp":1737614614229},{"id":"FBeb.js","timestamp":1737614646769},{"id":"zm0J.js","timestamp":1737719009190},{"id":"6CfM.js","timestamp":1737719129885},{"id":"dVKf.js","timestamp":1738064072614},{"id":"0i8F.js","timestamp":1738064153763},{"id":"If1F.js","source":"undoRedo.source","timestamp":1738064155437},{"id":"sWQK.js","timestamp":1738064167505}]}